LICENSE
whatnot/__init__.py
whatnot/exceptions.py
whatnot/types.py
whatnot/utils.py
whatnot/whatnot.py
whatnot-0.1.2.dist-info/LICENSE
whatnot-0.1.2.dist-info/WHEEL
whatnot-0.1.2.dist-info/METADATA
whatnot-0.1.2.dist-info/RECORD
